odoo/addons/shopfloor_mobile_base_auth_api_key/README.rst
odoo/addons/shopfloor_mobile_base_auth_api_key/__init__.py
odoo/addons/shopfloor_mobile_base_auth_api_key/__manifest__.py
odoo/addons/shopfloor_mobile_base_auth_api_key/demo/auth_api_key_demo.xml
odoo/addons/shopfloor_mobile_base_auth_api_key/demo/auth_api_key_group_demo.xml
odoo/addons/shopfloor_mobile_base_auth_api_key/demo/shopfloor_app_demo.xml
odoo/addons/shopfloor_mobile_base_auth_api_key/i18n/pt_BR.po
odoo/addons/shopfloor_mobile_base_auth_api_key/i18n/shopfloor_mobile_base_auth_api_key.pot
odoo/addons/shopfloor_mobile_base_auth_api_key/models/__init__.py
odoo/addons/shopfloor_mobile_base_auth_api_key/models/shopfloor_app.py
odoo/addons/shopfloor_mobile_base_auth_api_key/readme/CONTRIBUTORS.rst
odoo/addons/shopfloor_mobile_base_auth_api_key/readme/CREDITS.rst
odoo/addons/shopfloor_mobile_base_auth_api_key/readme/DESCRIPTION.rst
odoo/addons/shopfloor_mobile_base_auth_api_key/services/__init__.py
odoo/addons/shopfloor_mobile_base_auth_api_key/services/service.py
odoo/addons/shopfloor_mobile_base_auth_api_key/static/description/icon.png
odoo/addons/shopfloor_mobile_base_auth_api_key/static/description/index.html
odoo/addons/shopfloor_mobile_base_auth_api_key/static/wms/src/login.js
odoo/addons/shopfloor_mobile_base_auth_api_key/templates/assets.xml
odoo/addons/shopfloor_mobile_base_auth_api_key/views/shopfloor_app.xml
odoo14_addon_shopfloor_mobile_base_auth_api_key-14.0.2.1.0.dist-info/METADATA
odoo14_addon_shopfloor_mobile_base_auth_api_key-14.0.2.1.0.dist-info/WHEEL
odoo14_addon_shopfloor_mobile_base_auth_api_key-14.0.2.1.0.dist-info/top_level.txt
odoo14_addon_shopfloor_mobile_base_auth_api_key-14.0.2.1.0.dist-info/RECORD
