Metadata-Version: 2.1
Name: odoo14-addon-shopfloor-mobile-base-auth-api-key
Version: 14.0.2.1.0
Summary: Provides authentication via API key to Shopfloor base mobile app
Home-page: https://github.com/OCA/wms
Author: Camptocamp, Odoo Community Association (OCA)
Author-email: support@odoo-community.org
License: LGPL-3
Platform: UNKNOWN
Classifier: Programming Language :: Python
Classifier: Framework :: Odoo
Classifier: Framework :: Odoo :: 14.0
Classifier: License :: OSI Approved :: GNU Lesser General Public License v3 (LGPLv3)
Classifier: Development Status :: 4 - Beta
Requires-Python: >=3.6
Requires-Dist: odoo14-addon-auth-api-key-group
Requires-Dist: odoo14-addon-shopfloor-mobile-base
Requires-Dist: odoo (<14.1dev,>=14.0a)
